pipet/__init__.py
pipet/cli.py
pipet/forms.py
pipet/models.py
pipet/views.py
pipet/worker.py
pipet/api/__init__.py
pipet/api/tasks.py
pipet/api/views.py
pipet/sources/__init__.py
pipet/sources/intercom/__init__.py
pipet/sources/intercom/models.py
pipet/sources/stripe/__init__.py
pipet/sources/stripe/forms.py
pipet/sources/stripe/models.py
pipet/sources/stripe/tasks.py
pipet/sources/stripe/views.py
pipet/sources/zendesk/__init__.py
pipet/sources/zendesk/forms.py
pipet/sources/zendesk/models.py
pipet/sources/zendesk/tasks.py
pipet/sources/zendesk/views.py
pipet/utils/__init__.py
pipet/utils/celery.py
pipet-0.0.2.dist-info/METADATA
pipet-0.0.2.dist-info/RECORD
pipet-0.0.2.dist-info/WHEEL
pipet-0.0.2.dist-info/entry_points.txt
pipet-0.0.2.dist-info/top_level.txt
