Metadata-Version: 2.1
Name: pipet
Version: 0.0.2
Summary: Open SQL
Home-page: https://pipet.io
Author: Eric Feng
Author-email: erichfeng@gmail.com
License: Apache 2.0
Keywords: SQL
Platform: UNKNOWN
Classifier: Programming Language :: Python :: 3
Classifier: License :: OSI Approved :: Apache Software License
Classifier: Operating System :: OS Independent
Classifier: Development Status :: 1 - Planning
Classifier: Framework :: Flask
Classifier: Topic :: Utilities
Requires-Dist: alembic (==0.9.9)
Requires-Dist: amqp (==2.2.2)
Requires-Dist: aspy.yaml (==1.0.0)
Requires-Dist: billiard (==3.5.0.3)
Requires-Dist: blinker (==1.4)
Requires-Dist: cached-property (==1.4.0)
Requires-Dist: celery (==4.1.0)
Requires-Dist: celery-once (==2.0.0)
Requires-Dist: certifi (==2017.4.17)
Requires-Dist: chardet (==3.0.3)
Requires-Dist: click (==6.7)
Requires-Dist: contextlib2 (==0.5.5)
Requires-Dist: cookies (==2.2.1)
Requires-Dist: Faker (==0.8.16)
Requires-Dist: Flask (==1.0)
Requires-Dist: Flask-Admin (==1.5.0)
Requires-Dist: Flask-Alembic (==2.0.1)
Requires-Dist: Flask-Login (==0.4.0)
Requires-Dist: Flask-Migrate (==2.2.1)
Requires-Dist: Flask-SQLAlchemy (==2.2)
Requires-Dist: Flask-Testing (==0.7.1)
Requires-Dist: Flask-WTF (==0.14.2)
Requires-Dist: identify (==1.0.9)
Requires-Dist: idna (==2.5)
Requires-Dist: inflection (==0.3.1)
Requires-Dist: itsdangerous (==0.24)
Requires-Dist: Jinja2 (==2.10)
Requires-Dist: kombu (==4.1.0)
Requires-Dist: Mako (==1.0.7)
Requires-Dist: MarkupSafe (==1.0)
Requires-Dist: nodeenv (==1.3.0)
Requires-Dist: pre-commit (==1.4.3)
Requires-Dist: psycopg2 (==2.7.1)
Requires-Dist: py (==1.4.34)
Requires-Dist: pytest (==3.1.2)
Requires-Dist: python-dateutil (==2.7.2)
Requires-Dist: python-dotenv (==0.8.2)
Requires-Dist: python-editor (==1.0.3)
Requires-Dist: pytz (==2018.3)
Requires-Dist: PyYAML (==3.12)
Requires-Dist: raven (==6.7.0)
Requires-Dist: redis (==2.10.5)
Requires-Dist: requests (==2.17.3)
Requires-Dist: responses (==0.5.1)
Requires-Dist: rq (==0.8.0)
Requires-Dist: six (==1.10.0)
Requires-Dist: SQLAlchemy (==1.2.7)
Requires-Dist: stripe (==1.59.0)
Requires-Dist: text-unidecode (==1.2)
Requires-Dist: urllib3 (==1.21.1)
Requires-Dist: vine (==1.1.4)
Requires-Dist: virtualenv (==15.2.0)
Requires-Dist: Werkzeug (==0.14.1)
Requires-Dist: WTForms (==2.1)
